iosci/__init__.py
iosci/Podfile/CIComponentModel.py
iosci/Podfile/__init__.py
iosci/Util/CIShellCMD.py
iosci/Util/CIVersionManager.py
iosci/Util/__init__.py
iosci/xcode/CIPodfileParse.py
iosci/xcode/PodfileVersion.py
iosci/xcode/__init__.py
iosci/xcode/podfile.py
iosci-0.1.2.9.dist-info/LICENSE
iosci-0.1.2.9.dist-info/METADATA
iosci-0.1.2.9.dist-info/WHEEL
iosci-0.1.2.9.dist-info/top_level.txt
iosci-0.1.2.9.dist-info/RECORD
