Metadata-Version: 2.1
Name: iosci
Version: 0.1.2.9
Summary: T解析podfile和批量修改组件版本号.
Home-page: https://ziroom.com
Author: lichanghong
Author-email: lich7@ziroom.com
License: UNKNOWN
Platform: UNKNOWN
Classifier: License :: OSI Approved :: MIT License
Classifier: Intended Audience :: Developers
Classifier: Operating System :: OS Independent
Classifier: Programming Language :: Python
Classifier: Programming Language :: Python :: 3
Classifier: Programming Language :: Python :: 3.3
Classifier: Programming Language :: Python :: 3.4
Classifier: Programming Language :: Python :: 3.5
License-File: LICENSE
Requires-Dist: GitPython
